{
    "file_name": "0000000037.jpg",
    "label": "",
    "issues": [],
    "items": [
        {
            "id": "0",
            "language": "",
            "annotation_type": "default",
            "caseLabel": "test",
            "points": [
                [
                    2097.0,
                    856.0
                ],
                [
                    2113.0,
                    874.0
                ],
                [
                    2093.0,
                    890.0
                ],
                [
                    2078.0,
                    872.0
                ]
            ]
        },
        {
            "id": "1",
            "language": "",
            "annotation_type": "default",
            "caseLabel": "9999",
            "points": [
                [
                    2113.0,
                    874.0
                ],
                [
                    2134.0,
                    898.0
                ],
                [
                    2115.0,
                    915.0
                ],
                [
                    2094.0,
                    890.0
                ]
            ]
        },
        {
            "id": "2",
            "language": "",
            "annotation_type": "default",
            "caseLabel": "123",
            "points": [
                [
                    2131.0,
                    897.0
                ],
                [
                    2147.0,
                    916.0
                ],
                [
                    2128.0,
                    932.0
                ],
                [
                    2112.0,
                    913.0
                ]
            ]
        },
        {
            "id": "3",
            "language": "",
            "annotation_type": "default",
            "caseLabel": "string",
            "points": [
                [
                    2078.0,
                    872.0
                ],
                [
                    2112.0,
                    913.0
                ],
                [
                    2128.0,
                    932.0
                ],
                [
                    2147.0,
                    916.0
                ],
                [
                    2134.0,
                    898.0
                ],
                [
                    2113.0,
                    874.0
                ],
                [
                    2097.0,
                    856.0
                ]
            ]
        },
        {
            "id": "4",
            "language": "",
            "annotation_type": "default",
            "caseLabel": "test",
            "points": [
                [
                    145.48691099476446,
                    480.9528795811519
                ],
                [
                    697.4869109947645,
                    485.9528795811519
                ],
                [
                    693.4869109947645,
                    1009.9528795811518
                ],
                [
                    141.48691099476446,
                    1004.9528795811518
                ]
            ]
        },
        {
            "id": "5",
            "language": "",
            "annotation_type": "default",
            "caseLabel": "character",
            "points": [
                [
                    33.6806282722514,
                    1212.4816753926702
                ],
                [
                    585.6806282722514,
                    1217.4816753926702
                ],
                [
                    581.6806282722514,
                    1738.4816753926702
                ],
                [
                    29.680628272251397,
                    1733.4816753926702
                ]
            ]
        },
        {
            "id": "6",
            "language": "",
            "annotation_type": "default",
            "caseLabel": "character",
            "points": [
                [
                    169.66492146596852,
                    1778.392670157068
                ],
                [
                    721.6649214659685,
                    1783.392670157068
                ],
                [
                    717.6649214659685,
                    2278.392670157068
                ],
                [
                    165.66492146596852,
                    2273.392670157068
                ]
            ]
        },
        {
            "id": "7",
            "language": "",
            "annotation_type": "default",
            "caseLabel": "character",
            "points": [
                [
                    438.08900523560203,
                    978.3612565445026
                ],
                [
                    990.089005235602,
                    983.3612565445026
                ],
                [
                    986.089005235602,
                    1503.3612565445026
                ],
                [
                    434.08900523560203,
                    1498.3612565445026
                ]
            ]
        },
        {
            "id": "8",
            "language": "",
            "annotation_type": "default",
            "caseLabel": "abc",
            "points": [
                [
                    1597.5971799276508,
                    2074.7233608695906
                ],
                [
                    2149.5971799276504,
                    2079.7233608695906
                ],
                [
                    2159.5971799276504,
                    947.7233608695906
                ],
                [
                    2164.5971799276504,
                    368.72336086959075
                ],
                [
                    2168.5971799276504,
                    362.6768197088466
                ],
                [
                    1616.5971799276508,
                    362.6768197088466
                ],
                [
                    1601.5971799276508,
                    1554.723360869591
                ]
            ]
        },
        {
            "id": "9",
            "language": "zh",
            "annotation_type": "default",
            "caseLabel": "character",
            "points": [
                [
                    1562.268085106383,
                    102.83404255319151
                ],
                [
                    1742.268085106383,
                    103.83404255319151
                ],
                [
                    1741.268085106383,
                    271.8340425531915
                ],
                [
                    1561.268085106383,
                    270.8340425531915
                ]
            ]
        },
        {
            "id": "10",
            "language": "zh",
            "annotation_type": "default",
            "caseLabel": "character",
            "points": [
                [
                    994.5404255319149,
                    93.28510638297871
                ],
                [
                    1174.540425531915,
                    94.28510638297871
                ],
                [
                    1173.540425531915,
                    267.2851063829787
                ],
                [
                    993.5404255319149,
                    266.2851063829787
                ]
            ]
        },
        {
            "id": "11",
            "language": "zh",
            "annotation_type": "default",
            "caseLabel": "character",
            "points": [
                [
                    1253.9659574468085,
                    99.73617021276607
                ],
                [
                    1453.1744680851064,
                    88.5446808510639
                ],
                [
                    1432.9659574468085,
                    264.73617021276607
                ],
                [
                    1250.2130535397334,
                    271.0075535284999
                ]
            ]
        },
        {
            "id": "12",
            "language": "zh",
            "annotation_type": "default",
            "caseLabel": "character",
            "points": [
                [
                    1549.8510638297873,
                    526.4936170212766
                ],
                [
                    1729.8510638297873,
                    527.4936170212766
                ],
                [
                    1728.8510638297873,
                    697.4936170212766
                ],
                [
                    1548.8510638297873,
                    696.4936170212766
                ]
            ]
        },
        {
            "id": "13",
            "language": "zh",
            "annotation_type": "default",
            "caseLabel": "character",
            "points": [
                [
                    1028.0,
                    930.0
                ],
                [
                    1208.0,
                    931.0
                ],
                [
                    1207.0,
                    1098.0
                ],
                [
                    1027.0,
                    1097.0
                ]
            ]
        },
        {
            "id": "14",
            "language": "zh",
            "annotation_type": "default",
            "caseLabel": "character",
            "points": [
                [
                    1028.0,
                    1123.0
                ],
                [
                    1208.0,
                    1124.0
                ],
                [
                    1207.0,
                    1313.0
                ],
                [
                    1027.0,
                    1312.0
                ]
            ]
        },
        {
            "id": "15",
            "language": "zh",
            "annotation_type": "default",
            "caseLabel": "character",
            "points": [
                [
                    1027.0,
                    1333.0
                ],
                [
                    1207.0,
                    1334.0
                ],
                [
                    1206.0,
                    1522.0
                ],
                [
                    1026.0,
                    1521.0
                ]
            ]
        },
        {
            "id": "16",
            "language": "zh",
            "annotation_type": "default",
            "caseLabel": "character",
            "points": [
                [
                    1026.0,
                    1533.0
                ],
                [
                    1206.0,
                    1534.0
                ],
                [
                    1205.0,
                    1753.0
                ],
                [
                    1025.0,
                    1752.0
                ]
            ]
        },
        {
            "id": "17",
            "language": "zh",
            "annotation_type": "default",
            "caseLabel": "9999",
            "points": [
                [
                    1025.0,
                    1752.0
                ],
                [
                    1205.0,
                    1753.0
                ],
                [
                    1207.0,
                    1334.0
                ],
                [
                    1208.0,
                    1124.0
                ],
                [
                    1211.0,
                    287.0
                ],
                [
                    1211.0,
                    83.0
                ],
                [
                    1031.0,
                    82.0
                ],
                [
                    1030.0,
                    250.0
                ],
                [
                    1027.0,
                    1097.0
                ]
            ]
        }
    ]
}