{
    "file_name": "0000000088.jpg",
    "label": "",
    "issues": [],
    "items": [
        {
            "annotation_type": "default",
            "caseLabel": "character",
            "attributes": [
                {}
            ],
            "points": [
                [
                    70.0,
                    446.0
                ],
                [
                    256.0,
                    446.0
                ],
                [
                    256.0,
                    640.0
                ],
                [
                    70.0,
                    640.0
                ]
            ]
        },
        {
            "annotation_type": "default",
            "caseLabel": "character",
            "attributes": [
                {}
            ],
            "points": [
                [
                    813.9460869565216,
                    434.64695652173907
                ],
                [
                    999.9460869565216,
                    434.64695652173907
                ],
                [
                    999.9460869565216,
                    628.6469565217391
                ],
                [
                    813.9460869565216,
                    628.6469565217391
                ]
            ]
        },
        {
            "annotation_type": "default",
            "caseLabel": "character",
            "attributes": [
                {}
            ],
            "points": [
                [
                    476.0,
                    446.0
                ],
                [
                    662.0,
                    446.0
                ],
                [
                    662.0,
                    640.0
                ],
                [
                    476.0,
                    640.0
                ]
            ]
        },
        {
            "annotation_type": "default",
            "caseLabel": "character",
            "attributes": [
                {}
            ],
            "points": [
                [
                    689.0,
                    446.0
                ],
                [
                    860.0,
                    446.0
                ],
                [
                    860.0,
                    640.0
                ],
                [
                    689.0,
                    640.0
                ]
            ]
        },
        {
            "annotation_type": "default",
            "caseLabel": "character",
            "attributes": [
                {}
            ],
            "points": [
                [
                    885.6765217391304,
                    451.67652173913046
                ],
                [
                    1066.6765217391303,
                    451.67652173913046
                ],
                [
                    1066.6765217391303,
                    645.6765217391305
                ],
                [
                    885.6765217391304,
                    645.6765217391305
                ]
            ]
        },
        {
            "annotation_type": "default",
            "caseLabel": "character",
            "attributes": [
                {}
            ],
            "points": [
                [
                    1083.0,
                    457.3530434782608
                ],
                [
                    1275.0,
                    457.3530434782608
                ],
                [
                    1275.0,
                    651.3530434782608
                ],
                [
                    1083.0,
                    651.3530434782608
                ]
            ]
        },
        {
            "annotation_type": "default",
            "caseLabel": "character",
            "attributes": [
                {}
            ],
            "points": [
                [
                    1496.247096092925,
                    790.6673706441393
                ],
                [
                    1680.247096092925,
                    790.6673706441393
                ],
                [
                    1680.247096092925,
                    984.6673706441393
                ],
                [
                    1496.247096092925,
                    984.6673706441393
                ]
            ]
        },
        {
            "annotation_type": "default",
            "caseLabel": "character",
            "attributes": [
                {}
            ],
            "points": [
                [
                    1487.0,
                    446.0
                ],
                [
                    1659.0,
                    446.0
                ],
                [
                    1659.0,
                    640.0
                ],
                [
                    1487.0,
                    640.0
                ]
            ]
        },
        {
            "annotation_type": "default",
            "caseLabel": "character",
            "attributes": [
                {}
            ],
            "points": [
                [
                    1686.0,
                    446.0
                ],
                [
                    1857.0,
                    446.0
                ],
                [
                    1857.0,
                    640.0
                ],
                [
                    1686.0,
                    640.0
                ]
            ]
        },
        {
            "annotation_type": "default",
            "caseLabel": "string",
            "attributes": [
                {}
            ],
            "points": [
                [
                    18.911304347826047,
                    446.0
                ],
                [
                    18.911304347826047,
                    640.0
                ],
                [
                    1805.9113043478258,
                    640.0
                ],
                [
                    1805.9113043478258,
                    446.0
                ]
            ]
        },
        {
            "annotation_type": "default",
            "caseLabel": "character",
            "attributes": [
                {}
            ],
            "points": [
                [
                    69.0,
                    776.0
                ],
                [
                    263.0,
                    776.0
                ],
                [
                    263.0,
                    961.0
                ],
                [
                    69.0,
                    961.0
                ]
            ]
        },
        {
            "annotation_type": "default",
            "caseLabel": "character",
            "attributes": [
                {}
            ],
            "points": [
                [
                    269.3234782608696,
                    776.0
                ],
                [
                    458.3234782608696,
                    776.0
                ],
                [
                    458.3234782608696,
                    961.0
                ],
                [
                    269.3234782608696,
                    961.0
                ]
            ]
        },
        {
            "annotation_type": "default",
            "caseLabel": "character",
            "attributes": [
                {}
            ],
            "points": [
                [
                    471.0,
                    776.0
                ],
                [
                    661.0,
                    776.0
                ],
                [
                    661.0,
                    961.0
                ],
                [
                    471.0,
                    961.0
                ]
            ]
        },
        {
            "annotation_type": "default",
            "caseLabel": "character",
            "attributes": [
                {}
            ],
            "points": [
                [
                    686.0,
                    776.0
                ],
                [
                    860.0,
                    776.0
                ],
                [
                    860.0,
                    961.0
                ],
                [
                    686.0,
                    961.0
                ]
            ]
        },
        {
            "annotation_type": "default",
            "caseLabel": "character",
            "attributes": [
                {}
            ],
            "points": [
                [
                    887.0,
                    776.0
                ],
                [
                    1057.0,
                    776.0
                ],
                [
                    1057.0,
                    961.0
                ],
                [
                    887.0,
                    961.0
                ]
            ]
        },
        {
            "annotation_type": "default",
            "caseLabel": "string",
            "attributes": [
                {}
            ],
            "points": [
                [
                    69.0,
                    776.0
                ],
                [
                    69.0,
                    961.0
                ],
                [
                    1057.0,
                    961.0
                ],
                [
                    1057.0,
                    776.0
                ]
            ]
        },
        {
            "annotation_type": "default",
            "caseLabel": "character",
            "attributes": [
                {}
            ],
            "points": [
                [
                    59.0,
                    1098.0
                ],
                [
                    256.0,
                    1098.0
                ],
                [
                    256.0,
                    1287.0
                ],
                [
                    59.0,
                    1287.0
                ]
            ]
        },
        {
            "annotation_type": "default",
            "caseLabel": "character",
            "attributes": [
                {}
            ],
            "points": [
                [
                    270.0,
                    1098.0
                ],
                [
                    462.0,
                    1098.0
                ],
                [
                    462.0,
                    1287.0
                ],
                [
                    270.0,
                    1287.0
                ]
            ]
        },
        {
            "annotation_type": "default",
            "caseLabel": "character",
            "attributes": [
                {}
            ],
            "points": [
                [
                    473.0,
                    1098.0
                ],
                [
                    659.0,
                    1098.0
                ],
                [
                    659.0,
                    1287.0
                ],
                [
                    473.0,
                    1287.0
                ]
            ]
        },
        {
            "annotation_type": "default",
            "caseLabel": "character",
            "attributes": [
                {}
            ],
            "points": [
                [
                    683.0,
                    1098.0
                ],
                [
                    863.0,
                    1098.0
                ],
                [
                    863.0,
                    1287.0
                ],
                [
                    683.0,
                    1287.0
                ]
            ]
        },
        {
            "annotation_type": "default",
            "caseLabel": "character",
            "attributes": [
                {}
            ],
            "points": [
                [
                    902.0,
                    1098.0
                ],
                [
                    1040.0,
                    1098.0
                ],
                [
                    1040.0,
                    1287.0
                ],
                [
                    902.0,
                    1287.0
                ]
            ]
        },
        {
            "annotation_type": "default",
            "caseLabel": "character",
            "attributes": [
                {}
            ],
            "points": [
                [
                    1089.0,
                    1098.0
                ],
                [
                    1259.0,
                    1098.0
                ],
                [
                    1259.0,
                    1287.0
                ],
                [
                    1089.0,
                    1287.0
                ]
            ]
        },
        {
            "annotation_type": "default",
            "caseLabel": "character",
            "attributes": [
                {}
            ],
            "points": [
                [
                    1281.0,
                    1098.0
                ],
                [
                    1467.0,
                    1098.0
                ],
                [
                    1467.0,
                    1287.0
                ],
                [
                    1281.0,
                    1287.0
                ]
            ]
        },
        {
            "annotation_type": "default",
            "caseLabel": "character",
            "attributes": [
                {}
            ],
            "points": [
                [
                    1485.0,
                    1098.0
                ],
                [
                    1661.0,
                    1098.0
                ],
                [
                    1661.0,
                    1287.0
                ],
                [
                    1485.0,
                    1287.0
                ]
            ]
        },
        {
            "annotation_type": "default",
            "caseLabel": "character",
            "attributes": [
                {}
            ],
            "points": [
                [
                    1933.4607417932284,
                    447.1600780264497
                ],
                [
                    2340.956804554428,
                    338.75108029934336
                ],
                [
                    2193.3672393370366,
                    770.1667324732564
                ],
                [
                    1933.4607417932284,
                    636.1600780264497
                ]
            ]
        },
        {
            "annotation_type": "default",
            "caseLabel": "label_1",
            "attributes": [
                {}
            ],
            "points": [
                [
                    191.44579221350546,
                    143.84657526211603
                ],
                [
                    191.44579221350546,
                    332.846575262116
                ],
                [
                    1990.4457922135055,
                    332.846575262116
                ],
                [
                    1990.4457922135055,
                    143.84657526211603
                ]
            ]
        },
        {
            "annotation_type": "default",
            "caseLabel": "character",
            "attributes": [
                {}
            ],
            "points": [
                [
                    64.0,
                    1428.0
                ],
                [
                    255.0,
                    1428.0
                ],
                [
                    255.0,
                    1615.0
                ],
                [
                    64.0,
                    1615.0
                ]
            ]
        },
        {
            "annotation_type": "default",
            "caseLabel": "character",
            "attributes": [
                {}
            ],
            "points": [
                [
                    258.0,
                    1428.0
                ],
                [
                    454.0,
                    1428.0
                ],
                [
                    454.0,
                    1615.0
                ],
                [
                    258.0,
                    1615.0
                ]
            ]
        },
        {
            "annotation_type": "default",
            "caseLabel": "character",
            "attributes": [
                {}
            ],
            "points": [
                [
                    466.0,
                    1428.0
                ],
                [
                    662.0,
                    1428.0
                ],
                [
                    662.0,
                    1615.0
                ],
                [
                    466.0,
                    1615.0
                ]
            ]
        },
        {
            "annotation_type": "default",
            "caseLabel": "character",
            "attributes": [
                {}
            ],
            "points": [
                [
                    670.0,
                    1428.0
                ],
                [
                    868.0,
                    1428.0
                ],
                [
                    868.0,
                    1615.0
                ],
                [
                    670.0,
                    1615.0
                ]
            ]
        },
        {
            "annotation_type": "default",
            "caseLabel": "character",
            "attributes": [
                {}
            ],
            "points": [
                [
                    870.0,
                    1428.0
                ],
                [
                    1063.0,
                    1428.0
                ],
                [
                    1063.0,
                    1615.0
                ],
                [
                    870.0,
                    1615.0
                ]
            ]
        },
        {
            "annotation_type": "default",
            "caseLabel": "character",
            "attributes": [
                {}
            ],
            "points": [
                [
                    1082.0,
                    1428.0
                ],
                [
                    1262.0,
                    1428.0
                ],
                [
                    1262.0,
                    1615.0
                ],
                [
                    1082.0,
                    1615.0
                ]
            ]
        },
        {
            "annotation_type": "default",
            "caseLabel": "character",
            "attributes": [
                {}
            ],
            "points": [
                [
                    1301.0,
                    1428.0
                ],
                [
                    1449.0,
                    1428.0
                ],
                [
                    1449.0,
                    1615.0
                ],
                [
                    1301.0,
                    1615.0
                ]
            ]
        },
        {
            "annotation_type": "default",
            "caseLabel": "character",
            "attributes": [
                {}
            ],
            "points": [
                [
                    1502.0,
                    1428.0
                ],
                [
                    1657.0,
                    1428.0
                ],
                [
                    1657.0,
                    1615.0
                ],
                [
                    1502.0,
                    1615.0
                ]
            ]
        },
        {
            "annotation_type": "default",
            "caseLabel": "character",
            "attributes": [
                {}
            ],
            "points": [
                [
                    1684.0,
                    1428.0
                ],
                [
                    1851.0,
                    1428.0
                ],
                [
                    1851.0,
                    1615.0
                ],
                [
                    1684.0,
                    1615.0
                ]
            ]
        },
        {
            "annotation_type": "default",
            "caseLabel": "string",
            "attributes": [
                {}
            ],
            "points": [
                [
                    64.0,
                    1428.0
                ],
                [
                    64.0,
                    1615.0
                ],
                [
                    1851.0,
                    1615.0
                ],
                [
                    1851.0,
                    1428.0
                ]
            ]
        },
        {
            "annotation_type": "default",
            "caseLabel": "character",
            "attributes": [
                {}
            ],
            "points": [
                [
                    64.0,
                    1760.0
                ],
                [
                    261.0,
                    1760.0
                ],
                [
                    261.0,
                    1939.0
                ],
                [
                    64.0,
                    1939.0
                ]
            ]
        },
        {
            "annotation_type": "default",
            "caseLabel": "character",
            "attributes": [
                {}
            ],
            "points": [
                [
                    269.0,
                    1760.0
                ],
                [
                    464.0,
                    1760.0
                ],
                [
                    464.0,
                    1939.0
                ],
                [
                    269.0,
                    1939.0
                ]
            ]
        },
        {
            "annotation_type": "default",
            "caseLabel": "character",
            "attributes": [
                {}
            ],
            "points": [
                [
                    473.0,
                    1760.0
                ],
                [
                    664.0,
                    1760.0
                ],
                [
                    664.0,
                    1939.0
                ],
                [
                    473.0,
                    1939.0
                ]
            ]
        },
        {
            "annotation_type": "default",
            "caseLabel": "string",
            "attributes": [
                {}
            ],
            "points": [
                [
                    64.0,
                    1760.0
                ],
                [
                    64.0,
                    1939.0
                ],
                [
                    664.0,
                    1939.0
                ],
                [
                    664.0,
                    1760.0
                ]
            ]
        },
        {
            "annotation_type": "default",
            "caseLabel": "character",
            "attributes": [
                {}
            ],
            "points": [
                [
                    75.0,
                    2089.0
                ],
                [
                    253.0,
                    2087.0
                ],
                [
                    255.0,
                    2268.0
                ],
                [
                    77.0,
                    2270.0
                ]
            ]
        },
        {
            "annotation_type": "default",
            "caseLabel": "character",
            "attributes": [
                {}
            ],
            "points": [
                [
                    280.0,
                    2086.0
                ],
                [
                    466.0,
                    2084.0
                ],
                [
                    468.0,
                    2265.0
                ],
                [
                    282.0,
                    2267.0
                ]
            ]
        },
        {
            "annotation_type": "default",
            "caseLabel": "character",
            "attributes": [
                {}
            ],
            "points": [
                [
                    491.0,
                    2084.0
                ],
                [
                    655.0,
                    2082.0
                ],
                [
                    657.0,
                    2263.0
                ],
                [
                    493.0,
                    2265.0
                ]
            ]
        },
        {
            "annotation_type": "default",
            "caseLabel": "character",
            "attributes": [
                {}
            ],
            "points": [
                [
                    687.0,
                    2082.0
                ],
                [
                    866.0,
                    2080.0
                ],
                [
                    868.0,
                    2261.0
                ],
                [
                    689.0,
                    2263.0
                ]
            ]
        },
        {
            "annotation_type": "default",
            "caseLabel": "character",
            "attributes": [
                {}
            ],
            "points": [
                [
                    884.0,
                    2080.0
                ],
                [
                    1060.0,
                    2078.0
                ],
                [
                    1062.0,
                    2259.0
                ],
                [
                    886.0,
                    2261.0
                ]
            ]
        },
        {
            "annotation_type": "default",
            "caseLabel": "character",
            "attributes": [
                {}
            ],
            "points": [
                [
                    1092.0,
                    2078.0
                ],
                [
                    1260.0,
                    2076.0
                ],
                [
                    1262.0,
                    2257.0
                ],
                [
                    1094.0,
                    2259.0
                ]
            ]
        },
        {
            "annotation_type": "default",
            "caseLabel": "character",
            "attributes": [
                {}
            ],
            "points": [
                [
                    1296.0,
                    2076.0
                ],
                [
                    1455.0,
                    2074.0
                ],
                [
                    1457.0,
                    2255.0
                ],
                [
                    1298.0,
                    2257.0
                ]
            ]
        },
        {
            "annotation_type": "default",
            "caseLabel": "string",
            "attributes": [
                {}
            ],
            "points": [
                [
                    75.0,
                    2089.0
                ],
                [
                    77.0,
                    2270.0
                ],
                [
                    1298.0,
                    2257.0
                ],
                [
                    1457.0,
                    2255.0
                ],
                [
                    1455.0,
                    2074.0
                ],
                [
                    655.0,
                    2082.0
                ],
                [
                    466.0,
                    2084.0
                ],
                [
                    280.0,
                    2086.0
                ]
            ]
        },
        {
            "annotation_type": "default",
            "caseLabel": "character",
            "attributes": [
                {}
            ],
            "points": [
                [
                    73.0,
                    2412.0
                ],
                [
                    252.0,
                    2411.0
                ],
                [
                    253.0,
                    2597.0
                ],
                [
                    74.0,
                    2598.0
                ]
            ]
        },
        {
            "annotation_type": "default",
            "caseLabel": "character",
            "attributes": [
                {}
            ],
            "points": [
                [
                    282.0,
                    2410.0
                ],
                [
                    468.0,
                    2409.0
                ],
                [
                    469.0,
                    2595.0
                ],
                [
                    283.0,
                    2596.0
                ]
            ]
        },
        {
            "annotation_type": "default",
            "caseLabel": "character",
            "attributes": [
                {}
            ],
            "points": [
                [
                    484.0,
                    2409.0
                ],
                [
                    658.0,
                    2408.0
                ],
                [
                    659.0,
                    2594.0
                ],
                [
                    485.0,
                    2595.0
                ]
            ]
        },
        {
            "annotation_type": "default",
            "caseLabel": "character",
            "attributes": [
                {}
            ],
            "points": [
                [
                    689.0,
                    2408.0
                ],
                [
                    865.0,
                    2407.0
                ],
                [
                    866.0,
                    2593.0
                ],
                [
                    690.0,
                    2594.0
                ]
            ]
        },
        {
            "annotation_type": "default",
            "caseLabel": "character",
            "attributes": [
                {}
            ],
            "points": [
                [
                    881.0,
                    2407.0
                ],
                [
                    1065.0,
                    2406.0
                ],
                [
                    1066.0,
                    2592.0
                ],
                [
                    882.0,
                    2593.0
                ]
            ]
        },
        {
            "annotation_type": "default",
            "caseLabel": "character",
            "attributes": [
                {}
            ],
            "points": [
                [
                    1090.0,
                    2406.0
                ],
                [
                    1264.0,
                    2405.0
                ],
                [
                    1265.0,
                    2591.0
                ],
                [
                    1091.0,
                    2592.0
                ]
            ]
        },
        {
            "annotation_type": "default",
            "caseLabel": "character",
            "attributes": [
                {}
            ],
            "points": [
                [
                    1294.0,
                    2405.0
                ],
                [
                    1455.0,
                    2404.0
                ],
                [
                    1456.0,
                    2590.0
                ],
                [
                    1295.0,
                    2591.0
                ]
            ]
        },
        {
            "annotation_type": "default",
            "caseLabel": "string",
            "attributes": [
                {}
            ],
            "points": [
                [
                    73.0,
                    2412.0
                ],
                [
                    74.0,
                    2598.0
                ],
                [
                    253.0,
                    2597.0
                ],
                [
                    1295.0,
                    2591.0
                ],
                [
                    1456.0,
                    2590.0
                ],
                [
                    1455.0,
                    2404.0
                ],
                [
                    658.0,
                    2408.0
                ],
                [
                    468.0,
                    2409.0
                ],
                [
                    282.0,
                    2410.0
                ]
            ]
        },
        {
            "annotation_type": "default",
            "caseLabel": "character",
            "attributes": [
                {}
            ],
            "points": [
                [
                    73.0,
                    2742.0
                ],
                [
                    260.0,
                    2740.0
                ],
                [
                    262.0,
                    2928.0
                ],
                [
                    75.0,
                    2930.0
                ]
            ]
        },
        {
            "annotation_type": "default",
            "caseLabel": "character",
            "attributes": [
                {}
            ],
            "points": [
                [
                    281.0,
                    2740.0
                ],
                [
                    471.0,
                    2738.0
                ],
                [
                    473.0,
                    2926.0
                ],
                [
                    283.0,
                    2928.0
                ]
            ]
        },
        {
            "annotation_type": "default",
            "caseLabel": "character",
            "attributes": [
                {}
            ],
            "points": [
                [
                    480.0,
                    2738.0
                ],
                [
                    661.0,
                    2736.0
                ],
                [
                    663.0,
                    2924.0
                ],
                [
                    482.0,
                    2926.0
                ]
            ]
        },
        {
            "annotation_type": "default",
            "caseLabel": "character",
            "attributes": [
                {}
            ],
            "points": [
                [
                    685.0,
                    2736.0
                ],
                [
                    866.0,
                    2734.0
                ],
                [
                    868.0,
                    2922.0
                ],
                [
                    687.0,
                    2924.0
                ]
            ]
        },
        {
            "annotation_type": "default",
            "caseLabel": "character",
            "attributes": [
                {}
            ],
            "points": [
                [
                    881.0,
                    2735.0
                ],
                [
                    1066.0,
                    2733.0
                ],
                [
                    1068.0,
                    2921.0
                ],
                [
                    883.0,
                    2923.0
                ]
            ]
        },
        {
            "annotation_type": "default",
            "caseLabel": "character",
            "attributes": [
                {}
            ],
            "points": [
                [
                    1086.3234782608697,
                    2733.0
                ],
                [
                    1259.3234782608697,
                    2732.0
                ],
                [
                    1261.3234782608697,
                    2920.0
                ],
                [
                    1088.3234782608697,
                    2921.0
                ]
            ]
        },
        {
            "annotation_type": "default",
            "caseLabel": "character",
            "attributes": [
                {}
            ],
            "points": [
                [
                    1290.0,
                    2731.0
                ],
                [
                    1455.0,
                    2730.0
                ],
                [
                    1457.0,
                    2918.0
                ],
                [
                    1292.0,
                    2919.0
                ]
            ]
        },
        {
            "annotation_type": "default",
            "caseLabel": "string",
            "attributes": [
                {}
            ],
            "points": [
                [
                    73.0,
                    2742.0
                ],
                [
                    75.0,
                    2930.0
                ],
                [
                    1267.0,
                    2920.0
                ],
                [
                    1457.0,
                    2918.0
                ],
                [
                    1455.0,
                    2730.0
                ],
                [
                    1290.0,
                    2731.0
                ],
                [
                    866.0,
                    2734.0
                ],
                [
                    661.0,
                    2736.0
                ],
                [
                    260.0,
                    2740.0
                ]
            ]
        }
    ]
}